{"per_page":10,"total":4,"current":3,"data":[{"title":"2021年11月的第一场雪","date":"2021-11-06T18:04:08.000Z","date_formatted":{"ll":"2021年11月7日","L":"2021/11/07","MM-DD":"11-07"},"thumbnail":"https://tva1.sinaimg.cn/large/008i3skNly1gwkz3r6pstj30sg0lc43b.jpg","excerpt":"","link":"posts/11219","tags":["随想"]},{"title":"Memo","date":"2021-10-28T09:29:00.000Z","date_formatted":{"ll":"2021年10月28日","L":"2021/10/28","MM-DD":"10-28"},"thumbnail":"https://tva1.sinaimg.cn/large/008i3skNly1gwv08ty64aj31340m4761.jpg","excerpt":"","link":"posts/53100","tags":["Swift","开发","项目"]},{"title":"Maven","date":"2021-08-20T07:19:32.000Z","date_formatted":{"ll":"2021年8月20日","L":"2021/08/20","MM-DD":"08-20"},"excerpt":"","link":"posts/38008","tags":["开发"]},{"title":"BUAAOO-第四单元总结","date":"2021-06-26T03:23:00.000Z","date_formatted":{"ll":"2021年6月26日","L":"2021/06/26","MM-DD":"06-26"},"excerpt":"","link":"posts/8987","tags":["BUAA","面向对象"]},{"title":"BUAAOO-第三单元总结","date":"2021-05-29T03:54:00.000Z","date_formatted":{"ll":"2021年5月29日","L":"2021/05/29","MM-DD":"05-29"},"excerpt":"","link":"posts/4801","tags":["BUAA","面向对象"]},{"title":"C++基础","date":"2021-04-30T03:00:00.000Z","date_formatted":{"ll":"2021年4月30日","L":"2021/04/30","MM-DD":"04-30"},"excerpt":"","link":"posts/44178","tags":["BUAA","C++"]},{"title":"BUAAOO-第二单元总结","date":"2021-04-25T14:33:00.000Z","date_formatted":{"ll":"2021年4月25日","L":"2021/04/25","MM-DD":"04-25"},"excerpt":"","link":"posts/54734","tags":["BUAA","面向对象"]},{"title":"BUAAOO-第一单元总结","date":"2021-03-28T11:23:00.000Z","date_formatted":{"ll":"2021年3月28日","L":"2021/03/28","MM-DD":"03-28"},"excerpt":"","link":"posts/56284","tags":["BUAA","面向对象"]},{"title":"Hexo食用方法","date":"2020-12-21T15:34:37.000Z","date_formatted":{"ll":"2020年12月21日","L":"2020/12/21","MM-DD":"12-21"},"excerpt":"","link":"posts/27962","tags":["hexo"]},{"title":"Git","date":"2020-11-03T14:51:30.000Z","date_formatted":{"ll":"2020年11月3日","L":"2020/11/03","MM-DD":"11-03"},"excerpt":"","link":"posts/25246","tags":["开发"]}]}